{
  "_comment" : "Created with OWL2VOWL (version 0.3.2-SNAPSHOT), http://vowl.visualdataweb.org",
  "header" : {
    "languages" : [ "en", "undefined" ],
    "baseIris" : [ "http://www.w3.org/1999/02/22-rdf-syntax-ns", "https://w3id.org/enigma", "http://www.w3.org/2000/01/rdf-schema", "http://vivoweb.org/ontology/core", "http://purl.org/dc/terms", "http://www.w3.org/2001/XMLSchema", "http://xmlns.com/foaf/0.1" ],
    "title" : {
      "undefined" : "The Person Ontology"
    },
    "iri" : "https://w3id.org/enigma",
    "version" : "v1.1.0",
    "author" : [ "MiHyun Jang", "Neda Jahanshad", "Ryan Espiritu" ],
    "description" : {
      "en" : "A cohort ontology that describes persons participating in ENIGMA and their properties."
    },
    "other" : {
      "license" : [ {
        "identifier" : "license",
        "language" : "undefined",
        "value" : "http://creativecommons.org/licenses/by/2.0/",
        "type" : "iri"
      } ],
      "priorVersion" : [ {
        "identifier" : "priorVersion",
        "language" : "undefined",
        "value" : "https://w3id.org/enigma/person/1.0.0",
        "type" : "iri"
      } ],
      "creator" : [ {
        "identifier" : "creator",
        "language" : "undefined",
        "value" : "Neda Jahanshad",
        "type" : "label"
      }, {
        "identifier" : "creator",
        "language" : "undefined",
        "value" : "Ryan Espiritu",
        "type" : "label"
      }, {
        "identifier" : "creator",
        "language" : "undefined",
        "value" : "MiHyun Jang",
        "type" : "label"
      } ],
      "contributor" : [ {
        "identifier" : "contributor",
        "language" : "undefined",
        "value" : "Haripriya Dharmala",
        "type" : "label"
      }, {
        "identifier" : "contributor",
        "language" : "undefined",
        "value" : "Daniel Garijo",
        "type" : "label"
      }, {
        "identifier" : "contributor",
        "language" : "undefined",
        "value" : "Yolanda Gil",
        "type" : "label"
      } ],
      "preferredNamespacePrefix" : [ {
        "identifier" : "preferredNamespacePrefix",
        "language" : "undefined",
        "value" : "enigma",
        "type" : "label"
      } ],
      "preferredNamespaceUri" : [ {
        "identifier" : "preferredNamespaceUri",
        "language" : "undefined",
        "value" : "https://w3id.org/enigma#",
        "type" : "iri"
      } ],
      "versionInfo" : [ {
        "identifier" : "versionInfo",
        "language" : "undefined",
        "value" : "v1.1.0",
        "type" : "label"
      } ],
      "title" : [ {
        "identifier" : "title",
        "language" : "undefined",
        "value" : "The Person Ontology",
        "type" : "label"
      } ]
    }
  },
  "namespace" : [ ],
  "metrics" : {
    "classCount" : 10,
    "objectPropertyCount" : 17,
    "datatypePropertyCount" : 10,
    "individualCount" : 0
  },
  "class" : [ {
    "id" : "3",
    "type" : "owl:Class"
  }, {
    "id" : "5",
    "type" : "owl:equivalentClass"
  }, {
    "id" : "11",
    "type" : "owl:Class"
  }, {
    "id" : "2",
    "type" : "owl:equivalentClass"
  }, {
    "id" : "21",
    "type" : "owl:equivalentClass"
  }, {
    "id" : "1",
    "type" : "owl:Class"
  }, {
    "id" : "30",
    "type" : "rdfs:Literal"
  }, {
    "id" : "31",
    "type" : "owl:Thing"
  }, {
    "id" : "32",
    "type" : "owl:Thing"
  }, {
    "id" : "10",
    "type" : "owl:equivalentClass"
  }, {
    "id" : "8",
    "type" : "owl:Class"
  }, {
    "id" : "15",
    "type" : "owl:Thing"
  }, {
    "id" : "33",
    "type" : "rdfs:Literal"
  }, {
    "id" : "6",
    "type" : "rdfs:Datatype"
  }, {
    "id" : "28",
    "type" : "rdfs:Datatype"
  }, {
    "id" : "36",
    "type" : "rdfs:Datatype"
  }, {
    "id" : "37",
    "type" : "rdfs:Datatype"
  }, {
    "id" : "13",
    "type" : "rdfs:Datatype"
  }, {
    "id" : "39",
    "type" : "rdfs:Datatype"
  }, {
    "id" : "19",
    "type" : "owl:Thing"
  }, {
    "id" : "42",
    "type" : "rdfs:Literal"
  }, {
    "id" : "41",
    "type" : "owl:unionOf"
  }, {
    "id" : "23",
    "type" : "rdfs:Datatype"
  }, {
    "id" : "25",
    "type" : "owl:Class"
  } ],
  "classAttribute" : [ {
    "iri" : "https://w3id.org/enigma#Project",
    "baseIri" : "https://w3id.org/enigma",
    "instances" : 0,
    "annotations" : {
      "example" : [ {
        "identifier" : "example",
        "language" : "en",
        "value" : "SZPositiveSymptoms",
        "type" : "label"
      } ]
    },
    "label" : {
      "IRI-based" : "Project",
      "en" : "Project"
    },
    "comment" : {
      "en" : "Project encompassing cohort"
    },
    "id" : "3"
  }, {
    "iri" : "https://w3id.org/enigma#Person",
    "equivalent" : [ "10" ],
    "baseIri" : "https://w3id.org/enigma",
    "instances" : 0,
    "annotations" : {
      "example" : [ {
        "identifier" : "example",
        "language" : "en",
        "value" : "Theo van Erp",
        "type" : "label"
      } ]
    },
    "label" : {
      "IRI-based" : "Person",
      "en" : "Person"
    },
    "comment" : {
      "en" : "Individual involved with the cohort"
    },
    "attributes" : [ "equivalent" ],
    "id" : "5"
  }, {
    "iri" : "https://w3id.org/enigma#AcademicArticle",
    "baseIri" : "https://w3id.org/enigma",
    "instances" : 0,
    "label" : {
      "IRI-based" : "AcademicArticle",
      "en" : "Academic article"
    },
    "comment" : {
      "en" : "An academic article, submitted as a result of the work in an ENIGMA project"
    },
    "id" : "11"
  }, {
    "iri" : "http://xmlns.com/foaf/0.1/Organization",
    "baseIri" : "http://xmlns.com/foaf/0.1",
    "instances" : 0,
    "annotations" : {
      "isDefinedBy" : [ {
        "identifier" : "isDefinedBy",
        "language" : "undefined",
        "value" : "http://xmlns.com/foaf/0.1",
        "type" : "iri"
      } ]
    },
    "label" : {
      "IRI-based" : "Organization"
    },
    "comment" : {
      "en" : "An organization contributing to a given ENIGMA project"
    },
    "attributes" : [ "external", "equivalent" ],
    "id" : "2"
  }, {
    "iri" : "https://w3id.org/enigma#Organization",
    "equivalent" : [ "2" ],
    "baseIri" : "https://w3id.org/enigma",
    "instances" : 0,
    "label" : {
      "IRI-based" : "Organization",
      "en" : "Organization"
    },
    "comment" : {
      "en" : "An organization belonging to the ENIGMA consortium. Organization can be hospitals, universities, departments, etc."
    },
    "attributes" : [ "equivalent" ],
    "id" : "21"
  }, {
    "iri" : "https://w3id.org/enigma#QualifiedAffiliation",
    "baseIri" : "https://w3id.org/enigma",
    "instances" : 0,
    "label" : {
      "IRI-based" : "QualifiedAffiliation",
      "en" : "Qualified Affiliation"
    },
    "comment" : {
      "en" : "Used to specify additional details regarding an indvidual's affiliation with an organization (i.e. start and end dates, roles, etc.)"
    },
    "id" : "1"
  }, {
    "iri" : "http://www.w3.org/2000/01/rdf-schema#Literal",
    "id" : "30",
    "label" : {
      "IRI-based" : "Literal",
      "undefined" : "Literal"
    }
  }, {
    "iri" : "http://www.w3.org/2002/07/owl#Thing",
    "baseIri" : "http://owl2vowl.de",
    "id" : "31",
    "label" : {
      "undefined" : "Thing"
    }
  }, {
    "iri" : "http://www.w3.org/2002/07/owl#Thing",
    "baseIri" : "http://owl2vowl.de",
    "id" : "32",
    "label" : {
      "undefined" : "Thing"
    }
  }, {
    "iri" : "http://xmlns.com/foaf/0.1/Person",
    "baseIri" : "http://xmlns.com/foaf/0.1",
    "instances" : 0,
    "annotations" : {
      "isDefinedBy" : [ {
        "identifier" : "isDefinedBy",
        "language" : "en",
        "value" : "http://xmlns.com/foaf/0.1/",
        "type" : "label"
      } ]
    },
    "label" : {
      "IRI-based" : "Person"
    },
    "attributes" : [ "external", "equivalent" ],
    "id" : "10"
  }, {
    "iri" : "https://w3id.org/enigma#WorkingGroup",
    "baseIri" : "https://w3id.org/enigma",
    "instances" : 0,
    "annotations" : {
      "example" : [ {
        "identifier" : "example",
        "language" : "en",
        "value" : "BipolarWG",
        "type" : "label"
      } ]
    },
    "label" : {
      "IRI-based" : "WorkingGroup",
      "en" : "Working Group"
    },
    "comment" : {
      "en" : "Group of researchers studying a certain topic/disease"
    },
    "id" : "8"
  }, {
    "iri" : "http://www.w3.org/2002/07/owl#Thing",
    "baseIri" : "http://owl2vowl.de",
    "id" : "15",
    "label" : {
      "undefined" : "Thing"
    }
  }, {
    "iri" : "http://www.w3.org/2000/01/rdf-schema#Literal",
    "id" : "33",
    "label" : {
      "IRI-based" : "Literal",
      "undefined" : "Literal"
    }
  }, {
    "iri" : "http://www.w3.org/2001/XMLSchema#string",
    "baseIri" : "http://www.w3.org/2001/XMLSchema",
    "id" : "6",
    "label" : {
      "IRI-based" : "string"
    }
  }, {
    "iri" : "http://www.w3.org/2001/XMLSchema#string",
    "baseIri" : "http://www.w3.org/2001/XMLSchema",
    "id" : "28",
    "label" : {
      "IRI-based" : "string"
    }
  }, {
    "iri" : "http://www.w3.org/2001/XMLSchema#string",
    "baseIri" : "http://www.w3.org/2001/XMLSchema",
    "id" : "36",
    "label" : {
      "IRI-based" : "string"
    }
  }, {
    "iri" : "http://www.w3.org/2001/XMLSchema#string",
    "baseIri" : "http://www.w3.org/2001/XMLSchema",
    "id" : "37",
    "label" : {
      "IRI-based" : "string"
    }
  }, {
    "iri" : "http://www.w3.org/2001/XMLSchema#string",
    "baseIri" : "http://www.w3.org/2001/XMLSchema",
    "id" : "13",
    "label" : {
      "IRI-based" : "string"
    }
  }, {
    "iri" : "http://www.w3.org/2001/XMLSchema#string",
    "baseIri" : "http://www.w3.org/2001/XMLSchema",
    "id" : "39",
    "label" : {
      "IRI-based" : "string"
    }
  }, {
    "iri" : "http://www.w3.org/2002/07/owl#Thing",
    "baseIri" : "http://owl2vowl.de",
    "id" : "19",
    "label" : {
      "undefined" : "Thing"
    }
  }, {
    "iri" : "http://www.w3.org/2000/01/rdf-schema#Literal",
    "id" : "42",
    "label" : {
      "IRI-based" : "Literal",
      "undefined" : "Literal"
    }
  }, {
    "instances" : 0,
    "union" : [ "25", "5" ],
    "attributes" : [ "anonymous", "union" ],
    "id" : "41"
  }, {
    "iri" : "http://www.w3.org/2001/XMLSchema#string",
    "baseIri" : "http://www.w3.org/2001/XMLSchema",
    "id" : "23",
    "label" : {
      "IRI-based" : "string"
    }
  }, {
    "iri" : "https://w3id.org/enigma#Cohort",
    "baseIri" : "https://w3id.org/enigma",
    "instances" : 0,
    "annotations" : {
      "example" : [ {
        "identifier" : "example",
        "language" : "en",
        "value" : "ADNI: Alzheimer’s Disease Neuroimaging Initiative",
        "type" : "label"
      } ]
    },
    "label" : {
      "IRI-based" : "Cohort",
      "en" : "Cohort"
    },
    "comment" : {
      "en" : "A group of individuals studied by a working group, limited by certain inclusion and exclusion criteria"
    },
    "id" : "25"
  } ],
  "property" : [ {
    "id" : "0",
    "type" : "owl:objectProperty"
  }, {
    "id" : "4",
    "type" : "owl:datatypeProperty"
  }, {
    "id" : "7",
    "type" : "owl:objectProperty"
  }, {
    "id" : "12",
    "type" : "owl:datatypeProperty"
  }, {
    "id" : "14",
    "type" : "owl:objectProperty"
  }, {
    "id" : "9",
    "type" : "owl:objectProperty"
  }, {
    "id" : "18",
    "type" : "owl:objectProperty"
  }, {
    "id" : "22",
    "type" : "owl:datatypeProperty"
  }, {
    "id" : "24",
    "type" : "owl:objectProperty"
  }, {
    "id" : "27",
    "type" : "owl:datatypeProperty"
  }, {
    "id" : "29",
    "type" : "owl:datatypeProperty"
  }, {
    "id" : "34",
    "type" : "owl:objectProperty"
  }, {
    "id" : "38",
    "type" : "owl:datatypeProperty"
  }, {
    "id" : "40",
    "type" : "owl:objectProperty"
  }, {
    "id" : "43",
    "type" : "owl:datatypeProperty"
  }, {
    "id" : "26",
    "type" : "owl:objectProperty"
  }, {
    "id" : "45",
    "type" : "owl:objectProperty"
  }, {
    "id" : "17",
    "type" : "owl:objectProperty"
  }, {
    "id" : "16",
    "type" : "owl:objectProperty"
  }, {
    "id" : "46",
    "type" : "owl:objectProperty"
  }, {
    "id" : "47",
    "type" : "owl:datatypeProperty"
  }, {
    "id" : "20",
    "type" : "owl:objectProperty"
  }, {
    "id" : "35",
    "type" : "owl:objectProperty"
  }, {
    "id" : "44",
    "type" : "owl:objectProperty"
  }, {
    "id" : "48",
    "type" : "owl:datatypeProperty"
  }, {
    "id" : "49",
    "type" : "owl:objectProperty"
  } ],
  "propertyAttribute" : [ {
    "iri" : "https://w3id.org/enigma#forOrganization",
    "baseIri" : "https://w3id.org/enigma",
    "range" : "2",
    "annotations" : {
      "example" : [ {
        "identifier" : "example",
        "language" : "en",
        "value" : "JohnSmith hasQualifiedAffiliation \"QualifiedAffiliation\" forOrganization USC",
        "type" : "label"
      } ]
    },
    "label" : {
      "IRI-based" : "forOrganization",
      "en" : "for organization"
    },
    "domain" : "1",
    "comment" : {
      "en" : "Describes the organization associated with the qualified affiliation"
    },
    "attributes" : [ "object" ],
    "id" : "0"
  }, {
    "iri" : "https://w3id.org/enigma#hasDegree",
    "baseIri" : "https://w3id.org/enigma",
    "range" : "6",
    "annotations" : {
      "example" : [ {
        "identifier" : "example",
        "language" : "en",
        "value" : "JohnSmith hasDegree PhD",
        "type" : "label"
      } ]
    },
    "label" : {
      "IRI-based" : "hasDegree",
      "en" : "has degree"
    },
    "domain" : "5",
    "comment" : {
      "en" : "Describes what degree a person has (e.g., BsC, PhD, etc.)"
    },
    "attributes" : [ "datatype" ],
    "id" : "4"
  }, {
    "iri" : "https://w3id.org/enigma#hasWorkingGroupChair",
    "baseIri" : "https://w3id.org/enigma",
    "range" : "5",
    "annotations" : {
      "example" : [ {
        "identifier" : "example",
        "language" : "en",
        "value" : "BipolarWorkingGroup hasWorkingGroupChair JohnSmith",
        "type" : "label"
      } ]
    },
    "label" : {
      "IRI-based" : "hasWorkingGroupChair",
      "en" : "has working group chair"
    },
    "superproperty" : [ "9" ],
    "domain" : "8",
    "comment" : {
      "en" : "Describes the working groups that someone is a chair of"
    },
    "attributes" : [ "object" ],
    "id" : "7"
  }, {
    "iri" : "https://w3id.org/enigma#hasMiddleInitial",
    "baseIri" : "https://w3id.org/enigma",
    "range" : "13",
    "annotations" : {
      "example" : [ {
        "identifier" : "example",
        "language" : "undefined",
        "value" : "John A Smith hasMiddleInitial \"A\"",
        "type" : "label"
      } ]
    },
    "label" : {
      "IRI-based" : "hasMiddleInitial",
      "en" : "has middle initial"
    },
    "domain" : "5",
    "comment" : {
      "undefined" : "Describes middle initial of a person"
    },
    "attributes" : [ "datatype" ],
    "id" : "12"
  }, {
    "iri" : "https://w3id.org/enigma#hasEmail",
    "baseIri" : "https://w3id.org/enigma",
    "range" : "15",
    "annotations" : {
      "rationale" : [ {
        "identifier" : "rationale",
        "language" : "en",
        "value" : "Property added to facilitate interaction with domain and ranges in the wiki. It's equivalent to foaf:mbox",
        "type" : "label"
      } ]
    },
    "label" : {
      "IRI-based" : "hasEmail",
      "en" : "has email"
    },
    "superproperty" : [ "16" ],
    "domain" : "5",
    "comment" : {
      "en" : "Property that indicates which is the email of a person"
    },
    "attributes" : [ "object" ],
    "id" : "14"
  }, {
    "iri" : "https://w3id.org/enigma#hasWorkingGroupMember",
    "baseIri" : "https://w3id.org/enigma",
    "range" : "5",
    "annotations" : {
      "example" : [ {
        "identifier" : "example",
        "language" : "en",
        "value" : "BipolarWorkingGroup hasWorkingGroupMember JohnSmith",
        "type" : "label"
      } ]
    },
    "label" : {
      "IRI-based" : "hasWorkingGroupMember",
      "en" : "has working group member"
    },
    "superproperty" : [ "17" ],
    "domain" : "8",
    "subproperty" : [ "7" ],
    "comment" : {
      "en" : "Describes what working group a person is a member of"
    },
    "attributes" : [ "object" ],
    "id" : "9"
  }, {
    "iri" : "http://vivoweb.org/ontology/core#orcidId",
    "baseIri" : "http://vivoweb.org/ontology/core",
    "range" : "19",
    "annotations" : {
      "isDefinedBy" : [ {
        "identifier" : "isDefinedBy",
        "language" : "en",
        "value" : "http://vivoweb.org/ontology/core#",
        "type" : "label"
      } ]
    },
    "label" : {
      "IRI-based" : "orcidId"
    },
    "domain" : "19",
    "subproperty" : [ "20" ],
    "comment" : {
      "undefined" : "This is now an object property where the object value is a resource of the form <http://orcid.org/NNNN-NNNN-NNNN-NNNN>.  This is to support connecting VIVO and ORCID in the linked data web.   Note: a person can have multiple ORCID iDs."
    },
    "attributes" : [ "object", "external" ],
    "id" : "18"
  }, {
    "iri" : "https://w3id.org/enigma#hasCurrentJobTitle",
    "baseIri" : "https://w3id.org/enigma",
    "range" : "23",
    "annotations" : {
      "example" : [ {
        "identifier" : "example",
        "language" : "en",
        "value" : "JohnSmith hasCurrentJobTitle \"Postdoc\"",
        "type" : "label"
      } ]
    },
    "label" : {
      "IRI-based" : "hasCurrentJobTitle",
      "en" : "has current job title"
    },
    "domain" : "5",
    "comment" : {
      "en" : "Data property that aims to capture the current job title of a person. Examples are student, faculty, staff, postdoc, etc."
    },
    "attributes" : [ "datatype" ],
    "id" : "22"
  }, {
    "iri" : "https://w3id.org/enigma#hasMainPrincipalInvestigator",
    "baseIri" : "https://w3id.org/enigma",
    "range" : "5",
    "annotations" : {
      "example" : [ {
        "identifier" : "example",
        "language" : "en",
        "value" : "Cohort1 hasMainPrincipalInvestigatorof JohnSmith",
        "type" : "label"
      } ]
    },
    "label" : {
      "IRI-based" : "hasMainPrincipalInvestigator",
      "en" : "has main principal investigator"
    },
    "superproperty" : [ "26" ],
    "domain" : "25",
    "comment" : {
      "en" : "Describes which cohorts somone is a main PI of"
    },
    "attributes" : [ "object" ],
    "id" : "24"
  }, {
    "iri" : "https://w3id.org/enigma#hasFamilyName",
    "baseIri" : "https://w3id.org/enigma",
    "range" : "28",
    "annotations" : {
      "rationale" : [ {
        "identifier" : "rationale",
        "language" : "en",
        "value" : "Property added to restrict the domain to enigma:Person. This is done for facilitating the interaction with the wiki interface",
        "type" : "label"
      } ]
    },
    "label" : {
      "IRI-based" : "hasFamilyName",
      "en" : "has family name"
    },
    "domain" : "5",
    "comment" : {
      "en" : "The family name of some person."
    },
    "attributes" : [ "datatype" ],
    "id" : "27"
  }, {
    "iri" : "http://xmlns.com/foaf/0.1/givenName",
    "baseIri" : "http://xmlns.com/foaf/0.1",
    "range" : "30",
    "annotations" : {
      "isDefinedBy" : [ {
        "identifier" : "isDefinedBy",
        "language" : "undefined",
        "value" : "http://xmlns.com/foaf/0.1/",
        "type" : "iri"
      } ]
    },
    "label" : {
      "IRI-based" : "givenName"
    },
    "domain" : "10",
    "comment" : {
      "en" : "The given name of some person."
    },
    "attributes" : [ "external", "datatype" ],
    "id" : "29"
  }, {
    "iri" : "https://w3id.org/enigma#author",
    "baseIri" : "https://w3id.org/enigma",
    "range" : "5",
    "label" : {
      "IRI-based" : "author",
      "en" : "author"
    },
    "superproperty" : [ "35" ],
    "domain" : "11",
    "comment" : {
      "en" : "Property to describe the author of a publication in the context of an ENIGMA project"
    },
    "attributes" : [ "object" ],
    "id" : "34"
  }, {
    "iri" : "https://w3id.org/enigma#hasGivenName",
    "baseIri" : "https://w3id.org/enigma",
    "range" : "36",
    "annotations" : {
      "rationale" : [ {
        "identifier" : "rationale",
        "language" : "en",
        "value" : "Property added to restrict the domain to enigma:Person. This is done for facilitating the interaction with the wiki interface",
        "type" : "label"
      } ]
    },
    "label" : {
      "IRI-based" : "hasGivenName",
      "en" : "has given name"
    },
    "domain" : "5",
    "comment" : {
      "en" : "The given name of some person."
    },
    "attributes" : [ "datatype" ],
    "id" : "38"
  }, {
    "iri" : "https://w3id.org/enigma#hasHomePage",
    "baseIri" : "https://w3id.org/enigma",
    "range" : "32",
    "annotations" : {
      "rationale" : [ {
        "identifier" : "rationale",
        "language" : "en",
        "value" : "Property added to facilitate interaction with domain and ranges in the wiki. It's equivalent to foaf:homePage",
        "type" : "label"
      } ]
    },
    "label" : {
      "IRI-based" : "hasHomePage",
      "en" : "has home page"
    },
    "domain" : "41",
    "comment" : {
      "en" : "Property that describes the home page of a cohort or person"
    },
    "attributes" : [ "object" ],
    "id" : "40"
  }, {
    "iri" : "http://xmlns.com/foaf/0.1/familyName",
    "baseIri" : "http://xmlns.com/foaf/0.1",
    "range" : "33",
    "annotations" : {
      "isDefinedBy" : [ {
        "identifier" : "isDefinedBy",
        "language" : "en",
        "value" : "http://xmlns.com/foaf/0.1/",
        "type" : "label"
      } ]
    },
    "label" : {
      "IRI-based" : "familyName"
    },
    "domain" : "10",
    "comment" : {
      "undefined" : "The family name of some person."
    },
    "attributes" : [ "external", "datatype" ],
    "id" : "43"
  }, {
    "iri" : "https://w3id.org/enigma#hasPrincipalInvestigator",
    "baseIri" : "https://w3id.org/enigma",
    "range" : "5",
    "annotations" : {
      "example" : [ {
        "identifier" : "example",
        "language" : "en",
        "value" : "Cohort1 hasPrincipalInvestigator JohnSmith",
        "type" : "label"
      } ]
    },
    "label" : {
      "IRI-based" : "hasPrincipalInvestigator",
      "en" : "has principal investigator"
    },
    "superproperty" : [ "44" ],
    "domain" : "25",
    "subproperty" : [ "24" ],
    "comment" : {
      "en" : "Describes which cohorts somone is the principal investigator of"
    },
    "attributes" : [ "object" ],
    "id" : "26"
  }, {
    "iri" : "https://w3id.org/enigma#hasAffiliate",
    "baseIri" : "https://w3id.org/enigma",
    "range" : "5",
    "annotations" : {
      "example" : [ {
        "identifier" : "example",
        "language" : "en",
        "value" : "HarvardU hasAffiliate JohnSmith",
        "type" : "label"
      } ]
    },
    "label" : {
      "IRI-based" : "hasAffiliate",
      "en" : "has affiliate"
    },
    "superproperty" : [ "17" ],
    "domain" : "21",
    "comment" : {
      "en" : "Describes the organization's affiliates"
    },
    "attributes" : [ "object" ],
    "id" : "45"
  }, {
    "iri" : "http://xmlns.com/foaf/0.1/member",
    "baseIri" : "http://xmlns.com/foaf/0.1",
    "range" : "19",
    "annotations" : {
      "isDefinedBy" : [ {
        "identifier" : "isDefinedBy",
        "language" : "undefined",
        "value" : "http://xmlns.com/foaf/0.1/member",
        "type" : "iri"
      } ]
    },
    "label" : {
      "IRI-based" : "member"
    },
    "domain" : "19",
    "subproperty" : [ "9", "45" ],
    "attributes" : [ "object", "external" ],
    "id" : "17"
  }, {
    "iri" : "http://xmlns.com/foaf/0.1/mbox",
    "baseIri" : "http://xmlns.com/foaf/0.1",
    "range" : "31",
    "annotations" : {
      "isDefinedBy" : [ {
        "identifier" : "isDefinedBy",
        "language" : "en",
        "value" : "http://xmlns.com/foaf/0.1/",
        "type" : "label"
      } ]
    },
    "label" : {
      "IRI-based" : "mbox"
    },
    "domain" : "10",
    "subproperty" : [ "14" ],
    "comment" : {
      "undefined" : "A  personal mailbox, ie. an Internet mailbox associated with exactly one owner, the first owner of this mailbox. This is a 'static inverse functional property', in that  there is (across time and change) at most one individual that ever has any particular value for foaf:mbox."
    },
    "attributes" : [ "object", "external" ],
    "id" : "16"
  }, {
    "iri" : "http://purl.org/dc/terms/contributor",
    "baseIri" : "http://purl.org/dc/terms",
    "range" : "19",
    "annotations" : {
      "isDefinedBy" : [ {
        "identifier" : "isDefinedBy",
        "language" : "undefined",
        "value" : "http://purl.org/dc/terms/contributor",
        "type" : "iri"
      } ]
    },
    "label" : {
      "IRI-based" : "contributor"
    },
    "domain" : "19",
    "subproperty" : [ "35" ],
    "attributes" : [ "object", "external" ],
    "id" : "46"
  }, {
    "iri" : "https://w3id.org/enigma#hasResearchInterest",
    "baseIri" : "https://w3id.org/enigma",
    "range" : "39",
    "annotations" : {
      "example" : [ {
        "identifier" : "example",
        "language" : "en",
        "value" : "JohnSmith hasReasearchInterest \"bipolar disorder\", \"schizophrenia\"",
        "type" : "label"
      } ]
    },
    "label" : {
      "IRI-based" : "hasResearchInterest",
      "en" : "has research interest"
    },
    "domain" : "5",
    "comment" : {
      "en" : "Describes a research interest of a person"
    },
    "attributes" : [ "datatype" ],
    "id" : "47"
  }, {
    "iri" : "https://w3id.org/enigma#hasOrcidId",
    "baseIri" : "https://w3id.org/enigma",
    "range" : "15",
    "annotations" : {
      "rationale" : [ {
        "identifier" : "rationale",
        "language" : "en",
        "value" : "Property added to facilitate interaction with the wiki, making domains and ranges explicit",
        "type" : "label"
      } ]
    },
    "label" : {
      "IRI-based" : "hasOrcidId",
      "en" : "has ORCID Id"
    },
    "superproperty" : [ "18" ],
    "domain" : "5",
    "comment" : {
      "en" : "ORCID Id of a Person"
    },
    "attributes" : [ "object" ],
    "id" : "20"
  }, {
    "iri" : "http://purl.org/dc/terms/creator",
    "baseIri" : "http://purl.org/dc/terms",
    "range" : "19",
    "annotations" : {
      "isDefinedBy" : [ {
        "identifier" : "isDefinedBy",
        "language" : "undefined",
        "value" : "http://purl.org/dc/terms/creator",
        "type" : "iri"
      } ]
    },
    "label" : {
      "IRI-based" : "creator"
    },
    "superproperty" : [ "46" ],
    "domain" : "19",
    "subproperty" : [ "34" ],
    "attributes" : [ "object", "external" ],
    "id" : "35"
  }, {
    "iri" : "https://w3id.org/enigma#hasInvestigator",
    "baseIri" : "https://w3id.org/enigma",
    "range" : "5",
    "annotations" : {
      "example" : [ {
        "identifier" : "example",
        "language" : "en",
        "value" : "BipolarCohort hasInvestigator JohnSmith",
        "type" : "label"
      } ]
    },
    "label" : {
      "IRI-based" : "hasInvestigator",
      "en" : "has investigator"
    },
    "domain" : "25",
    "subproperty" : [ "26" ],
    "comment" : {
      "en" : "Describes the cohort that someone is investigator of"
    },
    "attributes" : [ "object" ],
    "id" : "44"
  }, {
    "iri" : "https://w3id.org/enigma#hasGrant",
    "baseIri" : "https://w3id.org/enigma",
    "range" : "37",
    "annotations" : {
      "example" : [ {
        "identifier" : "example",
        "language" : "en",
        "value" : "John Smith hasGrant \"U54EB020403 (NIH)\"",
        "type" : "label"
      } ]
    },
    "label" : {
      "IRI-based" : "hasGrant",
      "en" : "has grant"
    },
    "domain" : "5",
    "comment" : {
      "en" : "Data property that aims to capture the grants that have been obtained by a person, in order to properly list them in the acknowledgements of the corresponding publication"
    },
    "attributes" : [ "datatype" ],
    "id" : "48"
  }, {
    "iri" : "http://xmlns.com/foaf/0.1/homepage",
    "baseIri" : "http://xmlns.com/foaf/0.1",
    "range" : "31",
    "annotations" : {
      "isDefinedBy" : [ {
        "identifier" : "isDefinedBy",
        "language" : "undefined",
        "value" : "http://xmlns.com/foaf/0.1/",
        "type" : "iri"
      } ]
    },
    "label" : {
      "IRI-based" : "homepage"
    },
    "domain" : "10",
    "comment" : {
      "undefined" : "A homepage for some thing."
    },
    "attributes" : [ "object", "external" ],
    "id" : "49"
  } ]
}